{"nodes": [{"id": "c_users_roberto_documents_opennn_tests_quasi_newton_method_test_cpp", "label": "quasi_newton_method_test.cpp", "file_type": "code", "source_file": "tests/quasi_newton_method_test.cpp", "source_location": "L1"}, {"id": "tests_quasi_newton_method_test_test", "label": "TEST()", "file_type": "code", "source_file": "tests/quasi_newton_method_test.cpp", "source_location": "L11"}, {"id": "quasinewtonmethodtest", "label": "QuasiNewtonMethodTest", "file_type": "code", "source_file": "tests/quasi_newton_method_test.cpp", "source_location": "L11"}, {"id": "defaultconstructor", "label": "DefaultConstructor", "file_type": "code", "source_file": "tests/quasi_newton_method_test.cpp", "source_location": "L11"}, {"id": "generalconstructor", "label": "GeneralConstructor", "file_type": "code", "source_file": "tests/quasi_newton_method_test.cpp", "source_location": "L18"}, {"id": "bfgs_update", "label": "BFGS_Update", "file_type": "code", "source_file": "tests/quasi_newton_method_test.cpp", "source_location": "L29"}, {"id": "train", "label": "Train", "file_type": "code", "source_file": "tests/quasi_newton_method_test.cpp", "source_location": "L65"}], "edges": [{"source": "c_users_roberto_documents_opennn_tests_quasi_newton_method_test_cpp", "target": "c_users_roberto_documents_opennn_tests_pch_h", "relation": "imports", "context": "import", "confidence": "EXTRACTED", "source_file": "tests/quasi_newton_method_test.cpp", "source_location": "L1", "weight": 1.0}, {"source": "c_users_roberto_documents_opennn_tests_quasi_newton_method_test_cpp", "target": "c_users_roberto_documents_opennn_tests_numerical_derivatives_h", "relation": "imports", "context": "import", "confidence": "EXTRACTED", "source_file": "tests/quasi_newton_method_test.cpp", "source_location": "L2", "weight": 1.0}, {"source": "c_users_roberto_documents_opennn_tests_quasi_newton_method_test_cpp", "target": "c_users_roberto_documents_opennn_opennn_dataset_h", "relation": "imports", "context": "import", "confidence": "EXTRACTED", "source_file": "tests/quasi_newton_method_test.cpp", "source_location": "L3", "weight": 1.0}, {"source": "c_users_roberto_documents_opennn_tests_quasi_newton_method_test_cpp", "target": "c_users_roberto_documents_opennn_opennn_tabular_dataset_h", "relation": "imports", "context": "import", "confidence": "EXTRACTED", "source_file": "tests/quasi_newton_method_test.cpp", "source_location": "L4", "weight": 1.0}, {"source": "c_users_roberto_documents_opennn_tests_quasi_newton_method_test_cpp", "target": "c_users_roberto_documents_opennn_opennn_standard_networks_h", "relation": "imports", "context": "import", "confidence": "EXTRACTED", "source_file": "tests/quasi_newton_method_test.cpp", "source_location": "L5", "weight": 1.0}, {"source": "c_users_roberto_documents_opennn_tests_quasi_newton_method_test_cpp", "target": "c_users_roberto_documents_opennn_opennn_loss_h", "relation": "imports", "context": "import", "confidence": "EXTRACTED", "source_file": "tests/quasi_newton_method_test.cpp", "source_location": "L6", "weight": 1.0}, {"source": "c_users_roberto_documents_opennn_tests_quasi_newton_method_test_cpp", "target": "c_users_roberto_documents_opennn_opennn_quasi_newton_method_h", "relation": "imports", "context": "import", "confidence": "EXTRACTED", "source_file": "tests/quasi_newton_method_test.cpp", "source_location": "L7", "weight": 1.0}, {"source": "c_users_roberto_documents_opennn_tests_quasi_newton_method_test_cpp", "target": "tests_quasi_newton_method_test_test", "relation": "contains", "confidence": "EXTRACTED", "source_file": "tests/quasi_newton_method_test.cpp", "source_location": "L11", "weight": 1.0}, {"source": "tests_quasi_newton_method_test_test", "target": "quasinewtonmethodtest", "relation": "references", "confidence": "EXTRACTED", "source_file": "tests/quasi_newton_method_test.cpp", "source_location": "L11", "weight": 1.0, "context": "parameter_type"}, {"source": "tests_quasi_newton_method_test_test", "target": "defaultconstructor", "relation": "references", "confidence": "EXTRACTED", "source_file": "tests/quasi_newton_method_test.cpp", "source_location": "L11", "weight": 1.0, "context": "parameter_type"}, {"source": "c_users_roberto_documents_opennn_tests_quasi_newton_method_test_cpp", "target": "tests_quasi_newton_method_test_test", "relation": "contains", "confidence": "EXTRACTED", "source_file": "tests/quasi_newton_method_test.cpp", "source_location": "L18", "weight": 1.0}, {"source": "tests_quasi_newton_method_test_test", "target": "quasinewtonmethodtest", "relation": "references", "confidence": "EXTRACTED", "source_file": "tests/quasi_newton_method_test.cpp", "source_location": "L18", "weight": 1.0, "context": "parameter_type"}, {"source": "tests_quasi_newton_method_test_test", "target": "generalconstructor", "relation": "references", "confidence": "EXTRACTED", "source_file": "tests/quasi_newton_method_test.cpp", "source_location": "L18", "weight": 1.0, "context": "parameter_type"}, {"source": "c_users_roberto_documents_opennn_tests_quasi_newton_method_test_cpp", "target": "tests_quasi_newton_method_test_test", "relation": "contains", "confidence": "EXTRACTED", "source_file": "tests/quasi_newton_method_test.cpp", "source_location": "L29", "weight": 1.0}, {"source": "tests_quasi_newton_method_test_test", "target": "quasinewtonmethodtest", "relation": "references", "confidence": "EXTRACTED", "source_file": "tests/quasi_newton_method_test.cpp", "source_location": "L29", "weight": 1.0, "context": "parameter_type"}, {"source": "tests_quasi_newton_method_test_test", "target": "bfgs_update", "relation": "references", "confidence": "EXTRACTED", "source_file": "tests/quasi_newton_method_test.cpp", "source_location": "L29", "weight": 1.0, "context": "parameter_type"}, {"source": "c_users_roberto_documents_opennn_tests_quasi_newton_method_test_cpp", "target": "tests_quasi_newton_method_test_test", "relation": "contains", "confidence": "EXTRACTED", "source_file": "tests/quasi_newton_method_test.cpp", "source_location": "L65", "weight": 1.0}, {"source": "tests_quasi_newton_method_test_test", "target": "quasinewtonmethodtest", "relation": "references", "confidence": "EXTRACTED", "source_file": "tests/quasi_newton_method_test.cpp", "source_location": "L65", "weight": 1.0, "context": "parameter_type"}, {"source": "tests_quasi_newton_method_test_test", "target": "train", "relation": "references", "confidence": "EXTRACTED", "source_file": "tests/quasi_newton_method_test.cpp", "source_location": "L65", "weight": 1.0, "context": "parameter_type"}], "raw_calls": [{"caller_nid": "tests_quasi_newton_method_test_test", "callee": "EXPECT_EQ", "is_member_call": false, "source_file": "C:\\Users\\Roberto\\Documents\\opennn\\tests\\quasi_newton_method_test.cpp", "source_location": "L15"}, {"caller_nid": "tests_quasi_newton_method_test_test", "callee": "get_loss", "is_member_call": true, "source_file": "C:\\Users\\Roberto\\Documents\\opennn\\tests\\quasi_newton_method_test.cpp", "source_location": "L15"}, {"caller_nid": "tests_quasi_newton_method_test_test", "callee": "EXPECT_EQ", "is_member_call": false, "source_file": "C:\\Users\\Roberto\\Documents\\opennn\\tests\\quasi_newton_method_test.cpp", "source_location": "L25"}, {"caller_nid": "tests_quasi_newton_method_test_test", "callee": "get_loss", "is_member_call": true, "source_file": "C:\\Users\\Roberto\\Documents\\opennn\\tests\\quasi_newton_method_test.cpp", "source_location": "L25"}, {"caller_nid": "tests_quasi_newton_method_test_test", "callee": "set_data_random", "is_member_call": true, "source_file": "C:\\Users\\Roberto\\Documents\\opennn\\tests\\quasi_newton_method_test.cpp", "source_location": "L39"}, {"caller_nid": "tests_quasi_newton_method_test_test", "callee": "set_sample_roles", "is_member_call": true, "source_file": "C:\\Users\\Roberto\\Documents\\opennn\\tests\\quasi_newton_method_test.cpp", "source_location": "L40"}, {"caller_nid": "tests_quasi_newton_method_test_test", "callee": "set_error", "is_member_call": true, "source_file": "C:\\Users\\Roberto\\Documents\\opennn\\tests\\quasi_newton_method_test.cpp", "source_location": "L45"}, {"caller_nid": "tests_quasi_newton_method_test_test", "callee": "set_parameters_random", "is_member_call": true, "source_file": "C:\\Users\\Roberto\\Documents\\opennn\\tests\\quasi_newton_method_test.cpp", "source_location": "L49"}, {"caller_nid": "tests_quasi_newton_method_test_test", "callee": "calculate_gradient", "is_member_call": false, "source_file": "C:\\Users\\Roberto\\Documents\\opennn\\tests\\quasi_newton_method_test.cpp", "source_location": "L51"}, {"caller_nid": "tests_quasi_newton_method_test_test", "callee": "EXPECT_EQ", "is_member_call": false, "source_file": "C:\\Users\\Roberto\\Documents\\opennn\\tests\\quasi_newton_method_test.cpp", "source_location": "L54"}, {"caller_nid": "tests_quasi_newton_method_test_test", "callee": "size", "is_member_call": true, "source_file": "C:\\Users\\Roberto\\Documents\\opennn\\tests\\quasi_newton_method_test.cpp", "source_location": "L54"}, {"caller_nid": "tests_quasi_newton_method_test_test", "callee": "get_parameters_size", "is_member_call": true, "source_file": "C:\\Users\\Roberto\\Documents\\opennn\\tests\\quasi_newton_method_test.cpp", "source_location": "L54"}, {"caller_nid": "tests_quasi_newton_method_test_test", "callee": "calculate_inverse_hessian", "is_member_call": false, "source_file": "C:\\Users\\Roberto\\Documents\\opennn\\tests\\quasi_newton_method_test.cpp", "source_location": "L56"}, {"caller_nid": "tests_quasi_newton_method_test_test", "callee": "EXPECT_EQ", "is_member_call": false, "source_file": "C:\\Users\\Roberto\\Documents\\opennn\\tests\\quasi_newton_method_test.cpp", "source_location": "L58"}, {"caller_nid": "tests_quasi_newton_method_test_test", "callee": "rows", "is_member_call": true, "source_file": "C:\\Users\\Roberto\\Documents\\opennn\\tests\\quasi_newton_method_test.cpp", "source_location": "L58"}, {"caller_nid": "tests_quasi_newton_method_test_test", "callee": "cols", "is_member_call": true, "source_file": "C:\\Users\\Roberto\\Documents\\opennn\\tests\\quasi_newton_method_test.cpp", "source_location": "L58"}, {"caller_nid": "tests_quasi_newton_method_test_test", "callee": "size", "is_member_call": true, "source_file": "C:\\Users\\Roberto\\Documents\\opennn\\tests\\quasi_newton_method_test.cpp", "source_location": "L60"}, {"caller_nid": "tests_quasi_newton_method_test_test", "callee": "EXPECT_FALSE", "is_member_call": false, "source_file": "C:\\Users\\Roberto\\Documents\\opennn\\tests\\quasi_newton_method_test.cpp", "source_location": "L61"}, {"caller_nid": "tests_quasi_newton_method_test_test", "callee": "isnan", "is_member_call": false, "source_file": "C:\\Users\\Roberto\\Documents\\opennn\\tests\\quasi_newton_method_test.cpp", "source_location": "L61"}, {"caller_nid": "tests_quasi_newton_method_test_test", "callee": "numerical_inverse_hessian", "is_member_call": false, "source_file": "C:\\Users\\Roberto\\Documents\\opennn\\tests\\quasi_newton_method_test.cpp", "source_location": "L61"}, {"caller_nid": "tests_quasi_newton_method_test_test", "callee": "set_data_constant", "is_member_call": true, "source_file": "C:\\Users\\Roberto\\Documents\\opennn\\tests\\quasi_newton_method_test.cpp", "source_location": "L72"}, {"caller_nid": "tests_quasi_newton_method_test_test", "callee": "set_parameters_random", "is_member_call": true, "source_file": "C:\\Users\\Roberto\\Documents\\opennn\\tests\\quasi_newton_method_test.cpp", "source_location": "L75"}, {"caller_nid": "tests_quasi_newton_method_test_test", "callee": "set_error", "is_member_call": true, "source_file": "C:\\Users\\Roberto\\Documents\\opennn\\tests\\quasi_newton_method_test.cpp", "source_location": "L80"}, {"caller_nid": "tests_quasi_newton_method_test_test", "callee": "set_loss", "is_member_call": true, "source_file": "C:\\Users\\Roberto\\Documents\\opennn\\tests\\quasi_newton_method_test.cpp", "source_location": "L81"}, {"caller_nid": "tests_quasi_newton_method_test_test", "callee": "set_maximum_epochs", "is_member_call": true, "source_file": "C:\\Users\\Roberto\\Documents\\opennn\\tests\\quasi_newton_method_test.cpp", "source_location": "L85"}, {"caller_nid": "tests_quasi_newton_method_test_test", "callee": "set_display", "is_member_call": true, "source_file": "C:\\Users\\Roberto\\Documents\\opennn\\tests\\quasi_newton_method_test.cpp", "source_location": "L86"}, {"caller_nid": "tests_quasi_newton_method_test_test", "callee": "train", "is_member_call": true, "source_file": "C:\\Users\\Roberto\\Documents\\opennn\\tests\\quasi_newton_method_test.cpp", "source_location": "L88"}, {"caller_nid": "tests_quasi_newton_method_test_test", "callee": "EXPECT_LE", "is_member_call": false, "source_file": "C:\\Users\\Roberto\\Documents\\opennn\\tests\\quasi_newton_method_test.cpp", "source_location": "L90"}, {"caller_nid": "tests_quasi_newton_method_test_test", "callee": "get_epochs_number", "is_member_call": true, "source_file": "C:\\Users\\Roberto\\Documents\\opennn\\tests\\quasi_newton_method_test.cpp", "source_location": "L90"}, {"caller_nid": "tests_quasi_newton_method_test_test", "callee": "set_data_random", "is_member_call": true, "source_file": "C:\\Users\\Roberto\\Documents\\opennn\\tests\\quasi_newton_method_test.cpp", "source_location": "L95"}, {"caller_nid": "tests_quasi_newton_method_test_test", "callee": "set_parameters_random", "is_member_call": true, "source_file": "C:\\Users\\Roberto\\Documents\\opennn\\tests\\quasi_newton_method_test.cpp", "source_location": "L99"}, {"caller_nid": "tests_quasi_newton_method_test_test", "callee": "train", "is_member_call": true, "source_file": "C:\\Users\\Roberto\\Documents\\opennn\\tests\\quasi_newton_method_test.cpp", "source_location": "L101"}, {"caller_nid": "tests_quasi_newton_method_test_test", "callee": "get_training_error", "is_member_call": true, "source_file": "C:\\Users\\Roberto\\Documents\\opennn\\tests\\quasi_newton_method_test.cpp", "source_location": "L102"}, {"caller_nid": "tests_quasi_newton_method_test_test", "callee": "EXPECT_LT", "is_member_call": false, "source_file": "C:\\Users\\Roberto\\Documents\\opennn\\tests\\quasi_newton_method_test.cpp", "source_location": "L104"}, {"caller_nid": "tests_quasi_newton_method_test_test", "callee": "set_maximum_epochs", "is_member_call": true, "source_file": "C:\\Users\\Roberto\\Documents\\opennn\\tests\\quasi_newton_method_test.cpp", "source_location": "L108"}, {"caller_nid": "tests_quasi_newton_method_test_test", "callee": "train", "is_member_call": true, "source_file": "C:\\Users\\Roberto\\Documents\\opennn\\tests\\quasi_newton_method_test.cpp", "source_location": "L110"}, {"caller_nid": "tests_quasi_newton_method_test_test", "callee": "get_training_error", "is_member_call": true, "source_file": "C:\\Users\\Roberto\\Documents\\opennn\\tests\\quasi_newton_method_test.cpp", "source_location": "L111"}, {"caller_nid": "tests_quasi_newton_method_test_test", "callee": "EXPECT_LE", "is_member_call": false, "source_file": "C:\\Users\\Roberto\\Documents\\opennn\\tests\\quasi_newton_method_test.cpp", "source_location": "L113"}, {"caller_nid": "tests_quasi_newton_method_test_test", "callee": "set_parameters_random", "is_member_call": true, "source_file": "C:\\Users\\Roberto\\Documents\\opennn\\tests\\quasi_newton_method_test.cpp", "source_location": "L115"}, {"caller_nid": "tests_quasi_newton_method_test_test", "callee": "set_loss_goal", "is_member_call": true, "source_file": "C:\\Users\\Roberto\\Documents\\opennn\\tests\\quasi_newton_method_test.cpp", "source_location": "L119"}, {"caller_nid": "tests_quasi_newton_method_test_test", "callee": "set_minimum_loss_decrease", "is_member_call": true, "source_file": "C:\\Users\\Roberto\\Documents\\opennn\\tests\\quasi_newton_method_test.cpp", "source_location": "L120"}, {"caller_nid": "tests_quasi_newton_method_test_test", "callee": "set_maximum_epochs", "is_member_call": true, "source_file": "C:\\Users\\Roberto\\Documents\\opennn\\tests\\quasi_newton_method_test.cpp", "source_location": "L121"}, {"caller_nid": "tests_quasi_newton_method_test_test", "callee": "set_maximum_time", "is_member_call": true, "source_file": "C:\\Users\\Roberto\\Documents\\opennn\\tests\\quasi_newton_method_test.cpp", "source_location": "L122"}, {"caller_nid": "tests_quasi_newton_method_test_test", "callee": "train", "is_member_call": true, "source_file": "C:\\Users\\Roberto\\Documents\\opennn\\tests\\quasi_newton_method_test.cpp", "source_location": "L124"}, {"caller_nid": "tests_quasi_newton_method_test_test", "callee": "EXPECT_LE", "is_member_call": false, "source_file": "C:\\Users\\Roberto\\Documents\\opennn\\tests\\quasi_newton_method_test.cpp", "source_location": "L126"}, {"caller_nid": "tests_quasi_newton_method_test_test", "callee": "set_loss_goal", "is_member_call": true, "source_file": "C:\\Users\\Roberto\\Documents\\opennn\\tests\\quasi_newton_method_test.cpp", "source_location": "L130"}, {"caller_nid": "tests_quasi_newton_method_test_test", "callee": "set_minimum_loss_decrease", "is_member_call": true, "source_file": "C:\\Users\\Roberto\\Documents\\opennn\\tests\\quasi_newton_method_test.cpp", "source_location": "L131"}, {"caller_nid": "tests_quasi_newton_method_test_test", "callee": "set_maximum_epochs", "is_member_call": true, "source_file": "C:\\Users\\Roberto\\Documents\\opennn\\tests\\quasi_newton_method_test.cpp", "source_location": "L132"}, {"caller_nid": "tests_quasi_newton_method_test_test", "callee": "set_maximum_time", "is_member_call": true, "source_file": "C:\\Users\\Roberto\\Documents\\opennn\\tests\\quasi_newton_method_test.cpp", "source_location": "L133"}, {"caller_nid": "tests_quasi_newton_method_test_test", "callee": "train", "is_member_call": true, "source_file": "C:\\Users\\Roberto\\Documents\\opennn\\tests\\quasi_newton_method_test.cpp", "source_location": "L135"}, {"caller_nid": "tests_quasi_newton_method_test_test", "callee": "EXPECT_LE", "is_member_call": false, "source_file": "C:\\Users\\Roberto\\Documents\\opennn\\tests\\quasi_newton_method_test.cpp", "source_location": "L137"}]}